{
  "variants": {
    "axis=x,cover=none": {
      "model": "missingwilds:block/fallen_spruce_log",
      "y": 90
    },
    "axis=y,cover=none": {
      "model": "missingwilds:block/fallen_spruce_log",
      "x": 90
    },
    "axis=z,cover=none": {
      "model": "missingwilds:block/fallen_spruce_log"
    },
    "axis=x,cover=moss": {
      "model": "missingwilds:block/fallen_spruce_log_mossy",
      "y": 90
    },
    "axis=y,cover=moss": {
      "model": "missingwilds:block/fallen_spruce_log",
      "x": 90
    },
    "axis=z,cover=moss": {
      "model": "missingwilds:block/fallen_spruce_log_mossy"
    },
    "axis=x,cover=snow": {
      "model": "missingwilds:block/fallen_spruce_log_snowy",
      "y": 90
    },
    "axis=y,cover=snow": {
      "model": "missingwilds:block/fallen_spruce_log",
      "x": 90
    },
    "axis=z,cover=snow": {
      "model": "missingwilds:block/fallen_spruce_log_snowy"
    }
  }
}